submissions/HariBhaskaran_2023A8PS0822G/src/rtl/minutes_counter.v
module minutes_counter(
    input  wire       rst_n,
    input  wire       clk,
    input  wire       sec_count,
    input  wire       reset,
    output reg [7:0]  minutes
);

always @(posedge clk or negedge rst_n) begin
    if (!rst_n || reset) begin
        minutes <= 8'd0;
    end else if (sec_count) begin
        if (minutes == 8'd99)
            minutes <= 8'd0;
        else
            minutes <= minutes + 8'd1;
    end
end

endmodule

submissions/HariBhaskaran_2023A8PS0822G/src/rtl/seconds_counter.v
module seconds_counter (
    input  wire       clk,
    input  wire       rst_n,
    input  wire       enable,
    input  wire       reset,
    output reg  [5:0] seconds,
    output reg        sec_count
);

always @(posedge clk or negedge rst_n) begin
    if (!rst_n || reset) begin
        seconds   <= 6'd0;
        sec_count <= 1'b0;
    end else begin
        sec_count <= 1'b0;

        if (enable) begin
            if (seconds == 6'd59) begin
                seconds   <= 6'd0;
                sec_count <= 1'b1;
            end else begin
                seconds <= seconds + 6'd1;
            end
        end
    end
end

endmodule

submissions/HariBhaskaran_2023A8PS0822G/rtl/ctrl_fsm.v
module ctrl_fsm (
    input  wire       clk,
    input  wire       rst_n,
    input  wire       start,
    input  wire       stop,
    input  wire       reset,
    output reg        count_enable,
    output reg [1:0]  status
);

localparam IDLE    = 2'b00;
localparam RUNNING = 2'b01;
localparam PAUSED  = 2'b10;

reg [1:0] state, next_state;

// State register
always @(posedge clk or negedge rst_n) begin
    if (!rst_n)
        state <= IDLE;
    else
        state <= next_state;
end

// Next-state logic
always @(*) begin
    next_state = state;

    case (state)
        IDLE:    if (start) next_state = RUNNING;
        RUNNING: if (stop)  next_state = PAUSED;
        PAUSED:  if (start) next_state = RUNNING;
        default: next_state = IDLE;
    endcase

    if (reset)
        next_state = IDLE;
end

// Registered outputs (Moore FSM)
always @(posedge clk or negedge rst_n) begin
    if (!rst_n) begin
        status       <= IDLE;
        count_enable <= 1'b0;
    end else begin
        status       <= next_state;
        count_enable <= (next_state == RUNNING);
    end
end

endmodule

submissions/HariBhaskaran_2023A8PS0822G/src/rtl/stopwatch_top.v
module stopwatch_top (
    input  wire        clk,
    input  wire        rst_n,
    input  wire        start,
    input  wire        stop,
    input  wire        reset,
    output wire [7:0]  minutes,
    output wire [5:0]  seconds,
    output wire [1:0]  status
);

wire count_enable;
wire sec_count;

ctrl_fsm fsm (
    .clk(clk),
    .rst_n(rst_n),
    .start(start),
    .stop(stop),
    .reset(reset),
    .count_enable(count_enable),
    .status(status)
);

seconds_counter sec (
    .clk(clk),
    .rst_n(rst_n),
    .enable(count_enable),
    .reset(reset),
    .seconds(seconds),
    .sec_count(sec_count)
);

minutes_counter min (
    .clk(clk),
    .rst_n(rst_n),
    .sec_count(sec_count),
    .reset(reset),
    .minutes(minutes)
);

endmodule

submissions/HariBhaskaran_2023A8PS0822G/docs/trace.vcd
$version Generated by VerilatedVcd $end
$timescale 1ps $end
 $scope module TOP $end
  $var wire 1 # clk $end
  $var wire 1 $ rst_n $end
  $var wire 1 % start $end
  $var wire 1 & stop $end
  $var wire 1 ' reset $end
  $var wire 8 ( minutes [7:0] $end
  $var wire 6 ) seconds [5:0] $end
  $var wire 2 * status [1:0] $end
  $scope module stopwatch_top $end
   $var wire 1 # clk $end
   $var wire 1 $ rst_n $end
   $var wire 1 % start $end
   $var wire 1 & stop $end
   $var wire 1 ' reset $end
   $var wire 8 ( minutes [7:0] $end
   $var wire 6 ) seconds [5:0] $end
   $var wire 2 * status [1:0] $end
   $var wire 1 + count_enable $end
   $var wire 1 , sec_count $end
   $scope module fsm $end
    $var wire 1 # clk $end
    $var wire 1 $ rst_n $end
    $var wire 1 % start $end
    $var wire 1 & stop $end
    $var wire 1 ' reset $end
    $var wire 1 + count_enable $end
    $var wire 2 * status [1:0] $end
    $var wire 2 / IDLE [1:0] $end
    $var wire 2 0 RUNNING [1:0] $end
    $var wire 2 1 PAUSED [1:0] $end
    $var wire 2 - state [1:0] $end
    $var wire 2 . next_state [1:0] $end
   $upscope $end
   $scope module min $end
    $var wire 1 $ rst_n $end
    $var wire 1 # clk $end
    $var wire 1 , sec_count $end
    $var wire 1 ' reset $end
    $var wire 8 ( minutes [7:0] $end
   $upscope $end
   $scope module sec $end
    $var wire 1 # clk $end
    $var wire 1 $ rst_n $end
    $var wire 1 + enable $end
    $var wire 1 ' reset $end
    $var wire 6 ) seconds [5:0] $end
    $var wire 1 , sec_count $end
   $upscope $end
  $upscope $end
 $upscope $end
$enddefinitions $end


#0
0#
0$
0%
0&
0'
b00000000 (
b000000 )
b00 *
0+
0,
b00 -
b00 .
b00 /
b01 0
b10 1
#1
1#
#2
0#
#3
1#
#4
0#
#5
1#
#6
0#
#7
1#
#8
0#
#9
1#
#10
0#
1$
1%
b01 .
#11
1#
b01 *
1+
b01 -
#12
0#
0%
#13
1#
b000001 )
#14
0#
#15
1#
b000010 )
#16
0#
#17
1#
b000011 )
#18
0#
#19
1#
b000100 )
#20
0#
#21
1#
b000101 )
#22
0#
#23
1#
b000110 )
#24
0#
#25
1#
b000111 )
#26
0#
#27
1#
b001000 )
#28
0#
#29
1#
b001001 )
#30
0#
#31
1#
b001010 )
#32
0#
#33
1#
b001011 )
#34
0#
#35
1#
b001100 )
#36
0#
#37
1#
b001101 )
#38
0#
#39
1#
b001110 )
#40
0#
#41
1#
b001111 )
#42
0#
#43
1#
b010000 )
#44
0#
#45
1#
b010001 )
#46
0#
#47
1#
b010010 )
#48
0#
#49
1#
b010011 )
#50
0#
#51
1#
b010100 )
#52
0#
#53
1#
b010101 )
#54
0#
#55
1#
b010110 )
#56
0#
#57
1#
b010111 )
#58
0#
#59
1#
b011000 )
#60
0#
#61
1#
b011001 )
#62
0#
#63
1#
b011010 )
#64
0#
#65
1#
b011011 )
#66
0#
#67
1#
b011100 )
#68
0#
#69
1#
b011101 )
#70
0#
#71
1#
b011110 )
#72
0#
#73
1#
b011111 )
#74
0#
#75
1#
b100000 )
#76
0#
#77
1#
b100001 )
#78
0#
#79
1#
b100010 )
#80
0#
#81
1#
b100011 )
#82
0#
#83
1#
b100100 )
#84
0#
#85
1#
b100101 )
#86
0#
#87
1#
b100110 )
#88
0#
#89
1#
b100111 )
#90
0#
#91
1#
b101000 )
#92
0#
#93
1#
b101001 )
#94
0#
#95
1#
b101010 )
#96
0#
#97
1#
b101011 )
#98
0#
#99
1#
b101100 )
#100
0#
#101
1#
b101101 )
#102
0#
#103
1#
b101110 )
#104
0#
#105
1#
b101111 )
#106
0#
#107
1#
b110000 )
#108
0#
#109
1#
b110001 )
#110
0#
#111
1#
b110010 )
#112
0#
#113
1#
b110011 )
#114
0#
#115
1#
b110100 )
#116
0#
#117
1#
b110101 )
#118
0#
#119
1#
b110110 )
#120
0#
#121
1#
b110111 )
#122
0#
#123
1#
b111000 )
#124
0#
#125
1#
b111001 )
#126
0#
#127
1#
b111010 )
#128
0#
#129
1#
b111011 )
1,
#130
0#
#131
1#
b00000001 (
b000000 )
0,
#132
0#
#133
1#
b000001 )
#134
0#
#135
1#
b000010 )
#136
0#
#137
1#
b000011 )
#138
0#
#139
1#
b000100 )
#140
0#
#141
1#
b000101 )
#142
0#
#143
1#
b000110 )
#144
0#
#145
1#
b000111 )
#146
0#
#147
1#
b001000 )
#148
0#
#149
1#
b001001 )
#150
0#
#151
1#
b001010 )
#152
0#
1&
b10 .
#153
1#
b001011 )
b10 *
0+
b10 -
#154
0#
0&
#155
1#
#156
0#
#157
1#
#158
0#
#159
1#
#160
0#
#161
1#
#162
0#
#163
1#
#164
0#
#165
1#
#166
0#
#167
1#
#168
0#
#169
1#
#170
0#
#171
1#
#172
0#
#173
1#
#174
0#
1%
b01 .
#175
1#
b01 *
1+
b01 -
#176
0#
0%
#177
1#
b001100 )
#178
0#
#179
1#
b001101 )
#180
0#
#181
1#
b001110 )
#182
0#
#183
1#
b001111 )
#184
0#
#185
1#
b010000 )
#186
0#
#187
1#
b010001 )
#188
0#
#189
1#
b010010 )
#190
0#
#191
1#
b010011 )
#192
0#
#193
1#
b010100 )
#194
0#
#195
1#
b010101 )
#196
0#
#197
1#
b010110 )
#198
0#
#199
1#
b010111 )
#200
0#
#201
1#
b011000 )
#202
0#
#203
1#
b011001 )
#204
0#
#205
1#
b011010 )
#206
0#
#207
1#
b011011 )
#208
0#
#209
1#
b011100 )
#210
0#
#211
1#
b011101 )
#212
0#
#213
1#
b011110 )
#214
0#
#215
1#
b011111 )
#216
0#
1'
b00 .
#217
1#
b00000000 (
b000000 )
b00 *
0+
b00 -
#218
0#
0'
